odoo/addons/stock_route_location_source/README.rst
odoo/addons/stock_route_location_source/__init__.py
odoo/addons/stock_route_location_source/__manifest__.py
odoo/addons/stock_route_location_source/i18n/it.po
odoo/addons/stock_route_location_source/i18n/stock_route_location_source.pot
odoo/addons/stock_route_location_source/models/__init__.py
odoo/addons/stock_route_location_source/models/stock_route.py
odoo/addons/stock_route_location_source/readme/CONTRIBUTORS.md
odoo/addons/stock_route_location_source/readme/DESCRIPTION.md
odoo/addons/stock_route_location_source/static/description/icon.png
odoo/addons/stock_route_location_source/static/description/index.html
odoo/addons/stock_route_location_source/tests/__init__.py
odoo/addons/stock_route_location_source/tests/test_get_source_location.py
odoo_addon_stock_route_location_source-18.0.1.0.1.dist-info/METADATA
odoo_addon_stock_route_location_source-18.0.1.0.1.dist-info/WHEEL
odoo_addon_stock_route_location_source-18.0.1.0.1.dist-info/top_level.txt
odoo_addon_stock_route_location_source-18.0.1.0.1.dist-info/RECORD
